MANIFEST.in
README.md
setup.py
src/conductor/__init__.py
src/conductor.maya.egg-info/PKG-INFO
src/conductor.maya.egg-info/SOURCES.txt
src/conductor.maya.egg-info/dependency_links.txt
src/conductor.maya.egg-info/entry_points.txt
src/conductor.maya.egg-info/not-zip-safe
src/conductor.maya.egg-info/requires.txt
src/conductor.maya.egg-info/top_level.txt
src/conductor/maya/__init__.py
src/conductor/maya/__version__.py
src/conductor/maya/conductor.mod
src/conductor/maya/cli/__init__.py
src/conductor/maya/cli/setup_maya.py
src/conductor/maya/icons/conductor_logo_white.png
src/conductor/maya/lib/__init__.py
src/conductor/maya/lib/conductor_menu.py
src/conductor/maya/lib/const.py
src/conductor/maya/lib/instance_types.py
src/conductor/maya/lib/layer_utils.py
src/conductor/maya/lib/projects.py
src/conductor/maya/lib/software.py
src/conductor/maya/lib/submit.py
src/conductor/maya/lib/window.py
src/conductor/maya/lib/ae/AEcommon.py
src/conductor/maya/lib/ae/AEconductorRenderTemplate.py
src/conductor/maya/lib/ae/AEdestination.py
src/conductor/maya/lib/ae/AEemails.py
src/conductor/maya/lib/ae/AEenvironment.py
src/conductor/maya/lib/ae/AEextraAssets.py
src/conductor/maya/lib/ae/AEframes.py
src/conductor/maya/lib/ae/AEinstanceType.py
src/conductor/maya/lib/ae/AElayers.py
src/conductor/maya/lib/ae/AEmetadata.py
src/conductor/maya/lib/ae/AEoutput.py
src/conductor/maya/lib/ae/AEproject.py
src/conductor/maya/lib/ae/AEscrapers.py
src/conductor/maya/lib/ae/AEsoftware.py
src/conductor/maya/lib/ae/AEtaskTemplate.py
src/conductor/maya/lib/ae/__init__.py
src/conductor/maya/lib/nodes/__init__.py
src/conductor/maya/lib/nodes/conductorRender.py
src/conductor/maya/lib/scrapers/__init__.py
src/conductor/maya/lib/scrapers/scrape_filename_atts.py
src/conductor/maya/lib/scrapers/scrape_references.py
src/conductor/maya/lib/scrapers/scrape_xgen.py
src/conductor/maya/plug-ins/Conductor.py