Metadata-Version: 2.1
Name: conductor.maya
Version: 0.1.5
Summary: Maya plugin for Conductor Cloud Rendering Platform.
Home-page: https://github.com/AtomicConductor/conductor-maya
Author: conductor
Author-email: info@conductortech.com
License: UNKNOWN
Platform: UNKNOWN
Classifier: Operating System :: OS Independent
Classifier: Programming Language :: Python :: 2.7
Classifier: Programming Language :: Python
Classifier: Topic :: Multimedia :: Graphics :: 3D Rendering
Requires-Python: ~=2.7
